autotweety/__init__.py
autotweety/env.example.py
autotweety/env.py
autotweety/tweet.py
autotweety-0.1.dist-info/DESCRIPTION.rst
autotweety-0.1.dist-info/METADATA
autotweety-0.1.dist-info/metadata.json
autotweety-0.1.dist-info/RECORD
autotweety-0.1.dist-info/top_level.txt
autotweety-0.1.dist-info/WHEEL
