Metadata-Version: 2.0
Name: autotweety
Version: 0.1
Summary: Something that tweets
Home-page: https://github.com/localhuman/autotweet
Author: localhuman
Author-email: tasaunders@gmail.com
License: UNKNOWN
Download-URL: https://github.com/localhuman/autotweet/tarball/master
Keywords: twitter,@realDonaldTrump
Platform: UNKNOWN
Requires-Dist: python-twitter
